pygenetics/__init__.py
pygenetics/member.py
pygenetics/parameter.py
pygenetics/population.py
pygenetics/utils.py
pygenetics-1.0.1.dist-info/LICENSE
pygenetics-1.0.1.dist-info/METADATA
pygenetics-1.0.1.dist-info/WHEEL
pygenetics-1.0.1.dist-info/top_level.txt
pygenetics-1.0.1.dist-info/RECORD
