Metadata-Version: 2.1
Name: pygenetics
Version: 1.0.1
Summary: Genetic algorithm framework for tuning variables in user-suppled functions
Author-email: Travis Kessler <travis.j.kessler@gmail.com>
Project-URL: Homepage, https://github.com/tjkessler/pygenetics
Project-URL: Bug Tracker, https://github.com/tjkessler/pygenetics/issues
Classifier: Programming Language :: Python :: 3.11
Classifier: License :: OSI Approved :: Apache Software License
Classifier: Operating System :: OS Independent
Requires-Python: >=3.11
License-File: LICENSE
